aiopyupbit/__init__.py
aiopyupbit/errors.py
aiopyupbit/exchange_api.py
aiopyupbit/quotation_api.py
aiopyupbit/request_api.py
aiopyupbit-0.2.4.dist-info/LICENSE
aiopyupbit-0.2.4.dist-info/METADATA
aiopyupbit-0.2.4.dist-info/WHEEL
aiopyupbit-0.2.4.dist-info/top_level.txt
aiopyupbit-0.2.4.dist-info/RECORD
