Metadata-Version: 2.1
Name: aiopyupbit
Version: 0.2.4
Summary: python wrapper for upbit API for asyncio and Python
Home-page: https://github.com/codejune/aiopyupbit
Author: Codejune
Author-email: kbj9704@gmail.com
License: UNKNOWN
Platform: UNKNOWN
Classifier: Programming Language :: Python :: 3
Classifier: License :: OSI Approved :: Apache Software License
Classifier: Operating System :: OS Independent
Requires-Python: >=3.8
Requires-Dist: pandas (>=1.2.4)
Requires-Dist: aiohttp (>=3.7.4)
Requires-Dist: pyjwt (>=2.1.0)
Requires-Dist: pytz (>=2020.5)
Requires-Dist: python-dateutil (>=2.8.1)
Requires-Dist: six (>=1.15.0)
